django_backup_utils/__init__.py
django_backup_utils/admin.py
django_backup_utils/apps.py
django_backup_utils/exceptions.py
django_backup_utils/forms.py
django_backup_utils/helpers.py
django_backup_utils/models.py
django_backup_utils/urls.py
django_backup_utils/views.py
django_backup_utils/management/__init__.py
django_backup_utils/management/commands/__init__.py
django_backup_utils/management/commands/createbackup.py
django_backup_utils/management/commands/listbackups.py
django_backup_utils/management/commands/loadbackup.py
django_backup_utils/management/commands/syncbackups.py
django_backup_utils/migrations/0001_initial.py
django_backup_utils/migrations/0002_auto_20220707_1236.py
django_backup_utils/migrations/0003_auto_20220707_2028.py
django_backup_utils/migrations/0004_auto_20220708_2010.py
django_backup_utils/migrations/0005_backup_backup_directories_and_more.py
django_backup_utils/migrations/__init__.py
django_backup_utils/templates/django_backup_utils/backup_changelist.html
django_backup_utils/templates/django_backup_utils/backup_createbackup.html
django_backup_utils/templates/django_backup_utils/backup_loadbackup.html
django_backup_utils/tests/__init__.py
django_backup_utils/tests/loaddata.py
django_backup_utils-0.3.2.dist-info/licenses/LICENSE
django_backup_utils-0.3.2.dist-info/METADATA
django_backup_utils-0.3.2.dist-info/WHEEL
django_backup_utils-0.3.2.dist-info/top_level.txt
django_backup_utils-0.3.2.dist-info/RECORD
