Metadata-Version: 2.4
Name: django-backup-utils
Version: 0.3.2
Summary: A Django app to create and load backups.
Home-page: https://gitlab.com/bscherbaum/django-backup-utils
Author: Benjamin Scherbaum
License: MIT
Project-URL: Source, https://gitlab.com/bscherbaum/django-backup-utils
Classifier: Environment :: Web Environment
Classifier: Framework :: Django :: 3.0
Classifier: Framework :: Django :: 4.0
Classifier: Framework :: Django :: 5.0
Classifier: Intended Audience :: Developers
Classifier: Operating System :: OS Independent
Classifier: Programming Language :: Python :: 3.8
Classifier: Programming Language :: Python :: 3.9
Classifier: Programming Language :: Python :: 3.10
Classifier: Programming Language :: Python :: 3.11
Classifier: Programming Language :: Python :: 3.12
Classifier: Programming Language :: Python :: 3.13
Classifier: Programming Language :: Python :: 3.14
Requires-Python: >=3.8
License-File: LICENSE
Requires-Dist: Django>=3.0
Dynamic: license-file
